sdoc/__init__.py
sdoc/core.py
sdoc/data/sdoc.h5
cana_sdoc-0.11.dist-info/LICENSE
cana_sdoc-0.11.dist-info/METADATA
cana_sdoc-0.11.dist-info/WHEEL
cana_sdoc-0.11.dist-info/top_level.txt
cana_sdoc-0.11.dist-info/RECORD
