Metadata-Version: 2.1
Name: cana-sdoc
Version: 0.11
Summary: Small Database of Optical Constants
Home-page: https://github.com/depra/sdoc
Author: M. De Pra
Author-email: mariondepra@gmail.com
Maintainer: M. De Pra
Maintainer-email: mariondepra@gmail.com
License: MIT License
Platform: UNKNOWN
Requires-Python: >=3.6
Requires-Dist: numpy
Requires-Dist: pandas
Requires-Dist: h5py
